finra/__init__.py
finra/finra.py
finra-0.0.1.dist-info/LICENSE
finra-0.0.1.dist-info/METADATA
finra-0.0.1.dist-info/WHEEL
finra-0.0.1.dist-info/top_level.txt
finra-0.0.1.dist-info/RECORD
