Metadata-Version: 2.2
Name: finra
Version: 0.0.1
Summary: A simple python wrapper for interacting with the Financial Industry Regulation Authority Query API
Author-email: Nikhil Sunder <nsunder724@gmail.com>
Maintainer-email: Nikhil Sunder <nsunder724@gmail.com>
License:                     GNU GENERAL PUBLIC LICENSE
Project-URL: Repository, https://github.com/nikhilxsunder/finra
Project-URL: Issues, https://github.com/nikhilxsunder/finra/issues
Project-URL: Documentation, https://developer.finra.org/products/query-api
Keywords: legal,regulatory,api,finance,finra
Classifier: Programming Language :: Python :: 3
Classifier: License :: OSI Approved :: GNU Affero General Public License v3
Classifier: Operating System :: OS Independent
Classifier: Development Status :: 4 - Beta
Classifier: Intended Audience :: Financial and Insurance Industry
Classifier: Topic :: Office/Business :: Financial :: Investment
Requires-Python: >=3.8
License-File: LICENSE
Requires-Dist: requests
